{
  "_meta": {
    "app_name": "Compliance Tracker",
    "description": "Complete compliance tracker management"
  },
  "spec_name": "compliance_tracker_spec",
  "entities": [
    {
      "name": "Policy",
      "table": "compliance_policies",
      "description": "Policy",
      "fields": [
        {
          "name": "id",
          "db_type": "UUID DEFAULT gen_random_uuid() PRIMARY KEY",
          "ts_type": "string",
          "nullable": false,
          "editable": false,
          "show_in_table": false,
          "show_in_form": false,
          "input_component": "none",
          "display_component": "text"
        },
        {
          "name": "org_id",
          "db_type": "UUID NOT NULL",
          "ts_type": "string",
          "nullable": false,
          "editable": false,
          "show_in_table": false,
          "show_in_form": false,
          "input_component": "none",
          "display_component": "text"
        },
        {
          "name": "title",
          "db_type": "VARCHAR(255) NOT NULL",
          "ts_type": "string",
          "nullable": false,
          "editable": true,
          "show_in_table": true,
          "show_in_form": true,
          "input_component": "text_input",
          "display_component": "text"
        },
        {
          "name": "description",
          "db_type": "TEXT",
          "ts_type": "string",
          "nullable": true,
          "editable": true,
          "show_in_table": false,
          "show_in_form": true,
          "input_component": "textarea",
          "display_component": "text"
        },
        {
          "name": "category",
          "db_type": "VARCHAR(50) NOT NULL",
          "ts_type": "string",
          "nullable": false,
          "editable": true,
          "show_in_table": true,
          "show_in_form": true,
          "input_component": "select",
          "display_component": "status_badge",
          "enum_values": [
            "data_privacy",
            "security",
            "financial",
            "hr",
            "environmental",
            "safety"
          ],
          "badge_colors": {
            "data_privacy": "blue",
            "security": "red",
            "financial": "green",
            "hr": "purple",
            "environmental": "amber",
            "safety": "pink"
          }
        },
        {
          "name": "version",
          "db_type": "VARCHAR(20) NOT NULL",
          "ts_type": "string",
          "nullable": false,
          "editable": true,
          "show_in_table": true,
          "show_in_form": true,
          "input_component": "text_input",
          "display_component": "text"
        },
        {
          "name": "effective_date",
          "db_type": "DATE NOT NULL",
          "ts_type": "string",
          "nullable": false,
          "editable": true,
          "show_in_table": true,
          "show_in_form": true,
          "input_component": "date_picker",
          "display_component": "date"
        },
        {
          "name": "review_date",
          "db_type": "DATE",
          "ts_type": "string",
          "nullable": true,
          "editable": true,
          "show_in_table": true,
          "show_in_form": true,
          "input_component": "date_picker",
          "display_component": "date"
        },
        {
          "name": "owner",
          "db_type": "VARCHAR(255) NOT NULL",
          "ts_type": "string",
          "nullable": false,
          "editable": true,
          "show_in_table": true,
          "show_in_form": true,
          "input_component": "text_input",
          "display_component": "text"
        },
        {
          "name": "status",
          "db_type": "VARCHAR(50) NOT NULL",
          "ts_type": "string",
          "nullable": false,
          "editable": true,
          "show_in_table": true,
          "show_in_form": true,
          "input_component": "select",
          "display_component": "status_badge",
          "enum_values": [
            "draft",
            "active",
            "under_review",
            "deprecated"
          ],
          "badge_colors": {
            "draft": "slate",
            "active": "green",
            "under_review": "amber",
            "deprecated": "red"
          }
        },
        {
          "name": "created_at",
          "db_type": "TIMESTAMPTZ NOT NULL DEFAULT now()",
          "ts_type": "string",
          "nullable": false,
          "editable": false,
          "show_in_table": false,
          "show_in_form": false,
          "input_component": "none",
          "display_component": "date"
        },
        {
          "name": "updated_at",
          "db_type": "TIMESTAMPTZ NOT NULL DEFAULT now()",
          "ts_type": "string",
          "nullable": false,
          "editable": false,
          "show_in_table": false,
          "show_in_form": false,
          "input_component": "none",
          "display_component": "date"
        }
      ]
    },
    {
      "name": "Requirement",
      "table": "compliance_requirements",
      "description": "Requirement",
      "fields": [
        {
          "name": "id",
          "db_type": "UUID DEFAULT gen_random_uuid() PRIMARY KEY",
          "ts_type": "string",
          "nullable": false,
          "editable": false,
          "show_in_table": false,
          "show_in_form": false,
          "input_component": "none",
          "display_component": "text"
        },
        {
          "name": "org_id",
          "db_type": "UUID NOT NULL",
          "ts_type": "string",
          "nullable": false,
          "editable": false,
          "show_in_table": false,
          "show_in_form": false,
          "input_component": "none",
          "display_component": "text"
        },
        {
          "name": "policy_id",
          "db_type": "UUID NOT NULL",
          "ts_type": "string",
          "nullable": false,
          "editable": true,
          "show_in_table": true,
          "show_in_form": true,
          "input_component": "relation_select",
          "display_component": "relation_link",
          "fk_entity": "Policy"
        },
        {
          "name": "title",
          "db_type": "VARCHAR(255) NOT NULL",
          "ts_type": "string",
          "nullable": false,
          "editable": true,
          "show_in_table": true,
          "show_in_form": true,
          "input_component": "text_input",
          "display_component": "text"
        },
        {
          "name": "description",
          "db_type": "TEXT",
          "ts_type": "string",
          "nullable": true,
          "editable": true,
          "show_in_table": false,
          "show_in_form": true,
          "input_component": "textarea",
          "display_component": "text"
        },
        {
          "name": "regulation",
          "db_type": "VARCHAR(100) NOT NULL",
          "ts_type": "string",
          "nullable": false,
          "editable": true,
          "show_in_table": true,
          "show_in_form": true,
          "input_component": "select",
          "display_component": "text",
          "enum_values": [
            "GDPR",
            "SOX",
            "HIPAA",
            "PCI_DSS",
            "ISO27001",
            "SOC2",
            "CCPA"
          ]
        },
        {
          "name": "criticality",
          "db_type": "VARCHAR(20) NOT NULL",
          "ts_type": "string",
          "nullable": false,
          "editable": true,
          "show_in_table": true,
          "show_in_form": true,
          "input_component": "select",
          "display_component": "status_badge",
          "enum_values": [
            "mandatory",
            "recommended",
            "optional"
          ],
          "badge_colors": {
            "mandatory": "red",
            "recommended": "amber",
            "optional": "blue"
          }
        },
        {
          "name": "status",
          "db_type": "VARCHAR(50) NOT NULL",
          "ts_type": "string",
          "nullable": false,
          "editable": true,
          "show_in_table": true,
          "show_in_form": true,
          "input_component": "select",
          "display_component": "status_badge",
          "enum_values": [
            "compliant",
            "non_compliant",
            "partial",
            "not_assessed"
          ],
          "badge_colors": {
            "compliant": "green",
            "non_compliant": "red",
            "partial": "amber",
            "not_assessed": "slate"
          }
        },
        {
          "name": "due_date",
          "db_type": "DATE",
          "ts_type": "string",
          "nullable": true,
          "editable": true,
          "show_in_table": true,
          "show_in_form": true,
          "input_component": "date_picker",
          "display_component": "date"
        },
        {
          "name": "owner",
          "db_type": "VARCHAR(255) NOT NULL",
          "ts_type": "string",
          "nullable": false,
          "editable": true,
          "show_in_table": true,
          "show_in_form": true,
          "input_component": "text_input",
          "display_component": "text"
        },
        {
          "name": "created_at",
          "db_type": "TIMESTAMPTZ NOT NULL DEFAULT now()",
          "ts_type": "string",
          "nullable": false,
          "editable": false,
          "show_in_table": false,
          "show_in_form": false,
          "input_component": "none",
          "display_component": "date"
        },
        {
          "name": "updated_at",
          "db_type": "TIMESTAMPTZ NOT NULL DEFAULT now()",
          "ts_type": "string",
          "nullable": false,
          "editable": false,
          "show_in_table": false,
          "show_in_form": false,
          "input_component": "none",
          "display_component": "date"
        }
      ]
    },
    {
      "name": "Audit",
      "table": "compliance_audits",
      "description": "Audit",
      "fields": [
        {
          "name": "id",
          "db_type": "UUID DEFAULT gen_random_uuid() PRIMARY KEY",
          "ts_type": "string",
          "nullable": false,
          "editable": false,
          "show_in_table": false,
          "show_in_form": false,
          "input_component": "none",
          "display_component": "text"
        },
        {
          "name": "org_id",
          "db_type": "UUID NOT NULL",
          "ts_type": "string",
          "nullable": false,
          "editable": false,
          "show_in_table": false,
          "show_in_form": false,
          "input_component": "none",
          "display_component": "text"
        },
        {
          "name": "title",
          "db_type": "VARCHAR(255) NOT NULL",
          "ts_type": "string",
          "nullable": false,
          "editable": true,
          "show_in_table": true,
          "show_in_form": true,
          "input_component": "text_input",
          "display_component": "text"
        },
        {
          "name": "audit_type",
          "db_type": "VARCHAR(30) NOT NULL",
          "ts_type": "string",
          "nullable": false,
          "editable": true,
          "show_in_table": true,
          "show_in_form": true,
          "input_component": "select",
          "display_component": "status_badge",
          "enum_values": [
            "internal",
            "external",
            "regulatory",
            "certification"
          ],
          "badge_colors": {
            "internal": "blue",
            "external": "purple",
            "regulatory": "red",
            "certification": "green"
          }
        },
        {
          "name": "auditor",
          "db_type": "VARCHAR(255) NOT NULL",
          "ts_type": "string",
          "nullable": false,
          "editable": true,
          "show_in_table": true,
          "show_in_form": true,
          "input_component": "text_input",
          "display_component": "text"
        },
        {
          "name": "start_date",
          "db_type": "DATE NOT NULL",
          "ts_type": "string",
          "nullable": false,
          "editable": true,
          "show_in_table": true,
          "show_in_form": true,
          "input_component": "date_picker",
          "display_component": "date"
        },
        {
          "name": "end_date",
          "db_type": "DATE",
          "ts_type": "string",
          "nullable": true,
          "editable": true,
          "show_in_table": true,
          "show_in_form": true,
          "input_component": "date_picker",
          "display_component": "date"
        },
        {
          "name": "scope",
          "db_type": "TEXT",
          "ts_type": "string",
          "nullable": true,
          "editable": true,
          "show_in_table": false,
          "show_in_form": true,
          "input_component": "textarea",
          "display_component": "text"
        },
        {
          "name": "finding_count",
          "db_type": "INTEGER NOT NULL DEFAULT 0",
          "ts_type": "number",
          "nullable": false,
          "editable": false,
          "show_in_table": true,
          "show_in_form": false,
          "input_component": "number_input",
          "display_component": "text",
          "computed": "COUNT(findings)"
        },
        {
          "name": "status",
          "db_type": "VARCHAR(50) NOT NULL",
          "ts_type": "string",
          "nullable": false,
          "editable": true,
          "show_in_table": true,
          "show_in_form": true,
          "input_component": "select",
          "display_component": "status_badge",
          "enum_values": [
            "planned",
            "in_progress",
            "completed",
            "cancelled"
          ],
          "badge_colors": {
            "planned": "slate",
            "in_progress": "blue",
            "completed": "green",
            "cancelled": "red"
          }
        },
        {
          "name": "created_at",
          "db_type": "TIMESTAMPTZ NOT NULL DEFAULT now()",
          "ts_type": "string",
          "nullable": false,
          "editable": false,
          "show_in_table": false,
          "show_in_form": false,
          "input_component": "none",
          "display_component": "date"
        },
        {
          "name": "updated_at",
          "db_type": "TIMESTAMPTZ NOT NULL DEFAULT now()",
          "ts_type": "string",
          "nullable": false,
          "editable": false,
          "show_in_table": false,
          "show_in_form": false,
          "input_component": "none",
          "display_component": "date"
        }
      ]
    },
    {
      "name": "Finding",
      "table": "compliance_findings",
      "description": "Finding",
      "fields": [
        {
          "name": "id",
          "db_type": "UUID DEFAULT gen_random_uuid() PRIMARY KEY",
          "ts_type": "string",
          "nullable": false,
          "editable": false,
          "show_in_table": false,
          "show_in_form": false,
          "input_component": "none",
          "display_component": "text"
        },
        {
          "name": "org_id",
          "db_type": "UUID NOT NULL",
          "ts_type": "string",
          "nullable": false,
          "editable": false,
          "show_in_table": false,
          "show_in_form": false,
          "input_component": "none",
          "display_component": "text"
        },
        {
          "name": "audit_id",
          "db_type": "UUID NOT NULL",
          "ts_type": "string",
          "nullable": false,
          "editable": true,
          "show_in_table": true,
          "show_in_form": true,
          "input_component": "relation_select",
          "display_component": "relation_link",
          "fk_entity": "Audit"
        },
        {
          "name": "requirement_id",
          "db_type": "UUID",
          "ts_type": "string",
          "nullable": true,
          "editable": true,
          "show_in_table": true,
          "show_in_form": true,
          "input_component": "relation_select",
          "display_component": "relation_link",
          "fk_entity": "Requirement"
        },
        {
          "name": "title",
          "db_type": "VARCHAR(255) NOT NULL",
          "ts_type": "string",
          "nullable": false,
          "editable": true,
          "show_in_table": true,
          "show_in_form": true,
          "input_component": "text_input",
          "display_component": "text"
        },
        {
          "name": "description",
          "db_type": "TEXT",
          "ts_type": "string",
          "nullable": true,
          "editable": true,
          "show_in_table": false,
          "show_in_form": true,
          "input_component": "textarea",
          "display_component": "text"
        },
        {
          "name": "severity",
          "db_type": "VARCHAR(20) NOT NULL",
          "ts_type": "string",
          "nullable": false,
          "editable": true,
          "show_in_table": true,
          "show_in_form": true,
          "input_component": "select",
          "display_component": "status_badge",
          "enum_values": [
            "critical",
            "major",
            "minor",
            "observation"
          ],
          "badge_colors": {
            "critical": "red",
            "major": "amber",
            "minor": "blue",
            "observation": "slate"
          }
        },
        {
          "name": "risk_level",
          "db_type": "VARCHAR(20) NOT NULL",
          "ts_type": "string",
          "nullable": false,
          "editable": true,
          "show_in_table": true,
          "show_in_form": true,
          "input_component": "select",
          "display_component": "status_badge",
          "enum_values": [
            "high",
            "medium",
            "low"
          ],
          "badge_colors": {
            "high": "red",
            "medium": "amber",
            "low": "green"
          }
        },
        {
          "name": "status",
          "db_type": "VARCHAR(50) NOT NULL",
          "ts_type": "string",
          "nullable": false,
          "editable": true,
          "show_in_table": true,
          "show_in_form": true,
          "input_component": "select",
          "display_component": "status_badge",
          "enum_values": [
            "open",
            "in_remediation",
            "resolved",
            "accepted"
          ],
          "badge_colors": {
            "open": "red",
            "in_remediation": "amber",
            "resolved": "green",
            "accepted": "blue"
          }
        },
        {
          "name": "due_date",
          "db_type": "DATE",
          "ts_type": "string",
          "nullable": true,
          "editable": true,
          "show_in_table": true,
          "show_in_form": true,
          "input_component": "date_picker",
          "display_component": "date"
        },
        {
          "name": "created_at",
          "db_type": "TIMESTAMPTZ NOT NULL DEFAULT now()",
          "ts_type": "string",
          "nullable": false,
          "editable": false,
          "show_in_table": false,
          "show_in_form": false,
          "input_component": "none",
          "display_component": "date"
        },
        {
          "name": "updated_at",
          "db_type": "TIMESTAMPTZ NOT NULL DEFAULT now()",
          "ts_type": "string",
          "nullable": false,
          "editable": false,
          "show_in_table": false,
          "show_in_form": false,
          "input_component": "none",
          "display_component": "date"
        }
      ]
    },
    {
      "name": "Action",
      "table": "compliance_actions",
      "description": "Action",
      "fields": [
        {
          "name": "id",
          "db_type": "UUID DEFAULT gen_random_uuid() PRIMARY KEY",
          "ts_type": "string",
          "nullable": false,
          "editable": false,
          "show_in_table": false,
          "show_in_form": false,
          "input_component": "none",
          "display_component": "text"
        },
        {
          "name": "org_id",
          "db_type": "UUID NOT NULL",
          "ts_type": "string",
          "nullable": false,
          "editable": false,
          "show_in_table": false,
          "show_in_form": false,
          "input_component": "none",
          "display_component": "text"
        },
        {
          "name": "finding_id",
          "db_type": "UUID NOT NULL",
          "ts_type": "string",
          "nullable": false,
          "editable": true,
          "show_in_table": true,
          "show_in_form": true,
          "input_component": "relation_select",
          "display_component": "relation_link",
          "fk_entity": "Finding"
        },
        {
          "name": "title",
          "db_type": "VARCHAR(255) NOT NULL",
          "ts_type": "string",
          "nullable": false,
          "editable": true,
          "show_in_table": true,
          "show_in_form": true,
          "input_component": "text_input",
          "display_component": "text"
        },
        {
          "name": "description",
          "db_type": "TEXT",
          "ts_type": "string",
          "nullable": true,
          "editable": true,
          "show_in_table": false,
          "show_in_form": true,
          "input_component": "textarea",
          "display_component": "text"
        },
        {
          "name": "assignee",
          "db_type": "VARCHAR(255) NOT NULL",
          "ts_type": "string",
          "nullable": false,
          "editable": true,
          "show_in_table": true,
          "show_in_form": true,
          "input_component": "text_input",
          "display_component": "text"
        },
        {
          "name": "priority",
          "db_type": "VARCHAR(20) NOT NULL",
          "ts_type": "string",
          "nullable": false,
          "editable": true,
          "show_in_table": true,
          "show_in_form": true,
          "input_component": "select",
          "display_component": "status_badge",
          "enum_values": [
            "low",
            "medium",
            "high",
            "critical"
          ],
          "badge_colors": {
            "low": "slate",
            "medium": "blue",
            "high": "amber",
            "critical": "red"
          }
        },
        {
          "name": "due_date",
          "db_type": "DATE NOT NULL",
          "ts_type": "string",
          "nullable": false,
          "editable": true,
          "show_in_table": true,
          "show_in_form": true,
          "input_component": "date_picker",
          "display_component": "date"
        },
        {
          "name": "completed_date",
          "db_type": "DATE",
          "ts_type": "string",
          "nullable": true,
          "editable": true,
          "show_in_table": true,
          "show_in_form": true,
          "input_component": "date_picker",
          "display_component": "date",
          "visible_when": {
            "field": "status",
            "operator": "eq",
            "value": "completed"
          }
        },
        {
          "name": "status",
          "db_type": "VARCHAR(50) NOT NULL",
          "ts_type": "string",
          "nullable": false,
          "editable": true,
          "show_in_table": true,
          "show_in_form": true,
          "input_component": "select",
          "display_component": "status_badge",
          "enum_values": [
            "open",
            "in_progress",
            "completed",
            "overdue",
            "cancelled"
          ],
          "badge_colors": {
            "open": "blue",
            "in_progress": "amber",
            "completed": "green",
            "overdue": "red",
            "cancelled": "slate"
          }
        },
        {
          "name": "completion_pct",
          "db_type": "NUMERIC(5,2)",
          "ts_type": "number",
          "nullable": true,
          "editable": false,
          "show_in_table": true,
          "show_in_form": false,
          "input_component": "number_input",
          "display_component": "percentage"
        },
        {
          "name": "created_at",
          "db_type": "TIMESTAMPTZ NOT NULL DEFAULT now()",
          "ts_type": "string",
          "nullable": false,
          "editable": false,
          "show_in_table": false,
          "show_in_form": false,
          "input_component": "none",
          "display_component": "date"
        },
        {
          "name": "updated_at",
          "db_type": "TIMESTAMPTZ NOT NULL DEFAULT now()",
          "ts_type": "string",
          "nullable": false,
          "editable": false,
          "show_in_table": false,
          "show_in_form": false,
          "input_component": "none",
          "display_component": "date"
        }
      ]
    },
    {
      "name": "Evidence",
      "table": "compliance_evidence",
      "description": "Evidence",
      "fields": [
        {
          "name": "id",
          "db_type": "UUID DEFAULT gen_random_uuid() PRIMARY KEY",
          "ts_type": "string",
          "nullable": false,
          "editable": false,
          "show_in_table": false,
          "show_in_form": false,
          "input_component": "none",
          "display_component": "text"
        },
        {
          "name": "org_id",
          "db_type": "UUID NOT NULL",
          "ts_type": "string",
          "nullable": false,
          "editable": false,
          "show_in_table": false,
          "show_in_form": false,
          "input_component": "none",
          "display_component": "text"
        },
        {
          "name": "requirement_id",
          "db_type": "UUID NOT NULL",
          "ts_type": "string",
          "nullable": false,
          "editable": true,
          "show_in_table": true,
          "show_in_form": true,
          "input_component": "relation_select",
          "display_component": "relation_link",
          "fk_entity": "Requirement"
        },
        {
          "name": "finding_id",
          "db_type": "UUID",
          "ts_type": "string",
          "nullable": true,
          "editable": true,
          "show_in_table": true,
          "show_in_form": true,
          "input_component": "relation_select",
          "display_component": "relation_link",
          "fk_entity": "Finding"
        },
        {
          "name": "title",
          "db_type": "VARCHAR(255) NOT NULL",
          "ts_type": "string",
          "nullable": false,
          "editable": true,
          "show_in_table": true,
          "show_in_form": true,
          "input_component": "text_input",
          "display_component": "text"
        },
        {
          "name": "evidence_type",
          "db_type": "VARCHAR(30) NOT NULL",
          "ts_type": "string",
          "nullable": false,
          "editable": true,
          "show_in_table": true,
          "show_in_form": true,
          "input_component": "select",
          "display_component": "status_badge",
          "enum_values": [
            "document",
            "screenshot",
            "log",
            "report",
            "attestation",
            "test_result"
          ],
          "badge_colors": {
            "document": "blue",
            "screenshot": "green",
            "log": "purple",
            "report": "amber",
            "attestation": "pink",
            "test_result": "slate"
          }
        },
        {
          "name": "file_url",
          "db_type": "VARCHAR(500)",
          "ts_type": "string",
          "nullable": true,
          "editable": true,
          "show_in_table": false,
          "show_in_form": true,
          "input_component": "file_upload",
          "display_component": "file_link"
        },
        {
          "name": "collected_date",
          "db_type": "DATE NOT NULL",
          "ts_type": "string",
          "nullable": false,
          "editable": true,
          "show_in_table": true,
          "show_in_form": true,
          "input_component": "date_picker",
          "display_component": "date"
        },
        {
          "name": "collector",
          "db_type": "VARCHAR(255) NOT NULL",
          "ts_type": "string",
          "nullable": false,
          "editable": true,
          "show_in_table": true,
          "show_in_form": true,
          "input_component": "text_input",
          "display_component": "text"
        },
        {
          "name": "status",
          "db_type": "VARCHAR(50) NOT NULL",
          "ts_type": "string",
          "nullable": false,
          "editable": true,
          "show_in_table": true,
          "show_in_form": true,
          "input_component": "select",
          "display_component": "status_badge",
          "enum_values": [
            "pending_review",
            "approved",
            "rejected",
            "expired"
          ],
          "badge_colors": {
            "pending_review": "amber",
            "approved": "green",
            "rejected": "red",
            "expired": "slate"
          }
        },
        {
          "name": "created_at",
          "db_type": "TIMESTAMPTZ NOT NULL DEFAULT now()",
          "ts_type": "string",
          "nullable": false,
          "editable": false,
          "show_in_table": false,
          "show_in_form": false,
          "input_component": "none",
          "display_component": "date"
        },
        {
          "name": "updated_at",
          "db_type": "TIMESTAMPTZ NOT NULL DEFAULT now()",
          "ts_type": "string",
          "nullable": false,
          "editable": false,
          "show_in_table": false,
          "show_in_form": false,
          "input_component": "none",
          "display_component": "date"
        }
      ]
    }
  ]
}